terrajinja/imports/chef/__init__.py
terrajinja/imports/chef/py.typed
terrajinja/imports/chef/_jsii/__init__.py
terrajinja/imports/chef/_jsii/chef@0.0.0.jsii.tgz
terrajinja/imports/chef/client/__init__.py
terrajinja/imports/chef/data_bag/__init__.py
terrajinja/imports/chef/data_bag_item/__init__.py
terrajinja/imports/chef/environment/__init__.py
terrajinja/imports/chef/node/__init__.py
terrajinja/imports/chef/provider/__init__.py
terrajinja/imports/chef/role/__init__.py
terrajinja_imports_chef-0.4.6.dist-info/LICENSE
terrajinja_imports_chef-0.4.6.dist-info/METADATA
terrajinja_imports_chef-0.4.6.dist-info/WHEEL
terrajinja_imports_chef-0.4.6.dist-info/top_level.txt
terrajinja_imports_chef-0.4.6.dist-info/RECORD
